RegexGenerator/__init__.py
RegexGenerator/regex_generator.py
regex_generator_lib-1.0.0.dist-info/LICENSE
regex_generator_lib-1.0.0.dist-info/METADATA
regex_generator_lib-1.0.0.dist-info/WHEEL
regex_generator_lib-1.0.0.dist-info/top_level.txt
regex_generator_lib-1.0.0.dist-info/RECORD
